README.rst
setup.py
pysubman/__init__.py
pysubman.egg-info/PKG-INFO
pysubman.egg-info/SOURCES.txt
pysubman.egg-info/dependency_links.txt
pysubman.egg-info/not-zip-safe
pysubman.egg-info/requires.txt
pysubman.egg-info/top_level.txt
pysubman/beanstalk/__init__.py
pysubman/beanstalk/connection.py
pysubman/beanstalk/constants.py
pysubman/beanstalk/consumer.py
pysubman/beanstalk/job.py
pysubman/beanstalk/jobitem.py
pysubman/beanstalk/log.py
pysubman/beanstalk/producer.py
pysubman/beanstalk/service.py
pysubman/beanstalk/threadtube.py
pysubman/beanstalk/tube.py
pysubman/redis/__init__.py
pysubman/redis/client.py
pysubman/redis/service.py
pysubman/redis/subscribe.py
pysubman/redis/util.py