Metadata-Version: 1.0
Name: pysubman
Version: 1.20.1.2
Summary: kafka simple using
Home-page: https://github.com/nashuiliang
Author: chuangwang
Author-email: nashuiliang@gmail.com
License: Apache License 2.0
Keywords: kafka
Platform: UNKNOWN
